xync_script/__init__.py
xync_script/cycle.py
xync_script/earns_upd.py
xync_script/init.py
xync_script/loader.py
xync_script-0.0.16.dist-info/METADATA
xync_script-0.0.16.dist-info/WHEEL
xync_script-0.0.16.dist-info/top_level.txt
xync_script-0.0.16.dist-info/RECORD
