Metadata-Version: 2.4
Name: xync-script
Version: 0.0.16
Summary: Automate scripts for XyncNet
Author-email: Mike Artemiev <mixartemev@gmail.com>
License: EULA
Project-URL: Homepage, https://gitlab.com/XyncNet/script
Project-URL: Repository, https://gitlab.com/XyncNet/script
Keywords: cex
Requires-Python: >=3.11
Requires-Dist: xn-auth
Requires-Dist: xync-schema
Requires-Dist: xync-client
Provides-Extra: dev
Requires-Dist: pytest-asyncio; extra == "dev"
Requires-Dist: build; extra == "dev"
Requires-Dist: pre-commit; extra == "dev"
Requires-Dist: python-dotenv; extra == "dev"
Requires-Dist: twine; extra == "dev"
